jcson/__init__.py
jcson/jfixer.py
jcson/jpath.py
jcson-0.1.6.dist-info/LICENSE
jcson-0.1.6.dist-info/METADATA
jcson-0.1.6.dist-info/WHEEL
jcson-0.1.6.dist-info/top_level.txt
jcson-0.1.6.dist-info/RECORD
