Metadata-Version: 2.1
Name: jcson
Version: 0.1.6
Summary: jcson - enhanced json for configuration
Home-page: https://github.com/zakalibit/jcson
Author: Alex Revetchi
Author-email: alex.revetchi@gmail.com
License: License :: OSI Approved :: MIT License
Platform: Linux
Classifier: Development Status :: 2 - Pre-Alpha
Classifier: Intended Audience :: Developers
Classifier: Intended Audience :: Information Technology
Classifier: License :: OSI Approved :: MIT License
Classifier: Operating System :: POSIX
Classifier: Operating System :: POSIX :: Linux
Classifier: Programming Language :: Python
